skft/__init__.py
skft/football.py
skft-0.0.1.dist-info/LICENSE
skft-0.0.1.dist-info/METADATA
skft-0.0.1.dist-info/WHEEL
skft-0.0.1.dist-info/entry_points.txt
skft-0.0.1.dist-info/top_level.txt
skft-0.0.1.dist-info/RECORD
