Metadata-Version: 2.1
Name: skft
Version: 0.0.1
Summary: Simple package to parse football schedule for today from sky sports
Home-page: https://github.com/ilya-smut/skft
Author: Ilya Smut
Author-email: ilya.smut.off.g@gmail.com
License: GPL-3.0 license
Project-URL: Source Code, https://github.com/ilya-smut/skft
License-File: LICENSE
Requires-Dist: requests
Requires-Dist: beautifulsoup4
